simple_sdcm/__init__.py
simple_sdcm/client.py
simple_sdcm-0.0.3.dist-info/METADATA
simple_sdcm-0.0.3.dist-info/WHEEL
simple_sdcm-0.0.3.dist-info/top_level.txt
simple_sdcm-0.0.3.dist-info/RECORD
